{
  "SpriteSize"                              : 128, 
  "SceneFonts"                              : [
    {
      "name"  : "PixelLife", 
      "path"  : "res/fonts/pixellife/", 
      "svgId" : "pixellife_small_cap" 
    }
  ], 
  
  "SceneFullScreenOnFirstEvent"             : true, 
  "SceneIconUrl"                            : "res/images/icon.ico", 
  "SceneCursorUrl"                          : "res/cursors/transparent-cursor.cur", 
  "SceneTitle"                              : "Snipe Intruders v1.0.0", 
  "SceneBackgroundColor"                    : "#000000", 
  "SceneCanvasBackgroundColor"              : "#ffffff", 
  "SceneCanvasXMarginProportion"            : 1, 
  "SceneCanvasYMarginProportion"            : 2, 
  
  "IntroMessageMaxDelta"                    : 2, 
  "IntroMessageFadeOutMaxDelta"             : 100, 
  "IntroMessageBackgroundColor"             : "#ffffff", 
  "IntroMessageText"                        : "AN EDGAR ALEXANDER FRANCO VIDEOGAME", 
  "IntroMessageFont"                        : "28px Arial Black", 
  "IntroMessageColor"                       : "#000000", 
  "IntroMessageOpacitySpeed"                : 0.025, 
  
  "StartScreenLogoResizeMaxDelta"           : 1, 
  "StartScreenStartMessageMaxDelta"         : 15, 
  "StartScreenCopyrightText"                : "copyright 2015, edgar alexander franco, all rights reserved", 
  "StartScreenCopyrightMarginTop"           : 35, 
  "StartScreenCopyrightFont"                : "28px PixelLife", 
  "StartScreenCopyrightColor"               : "#222222", 
  "StartScreenLogoStartProportion"          : 0.1, 
  "StartScreenLogoEndWidthOffset"           : 500, 
  "StartScreenLogoProportionDiff"           : 0.075, 
  "StartScreenEsrbRatingMarginRight"        : 15, 
  "StartScreenEsrbRatingMarginBottom"       : 15, 
  "StartScreenStartMessageText"             : "click to start", 
  "StartScreenStartMessageMarginBottom"     : 15, 
  "StartScreenStartMessageFont"             : "48px PixelLife", 
  "StartScreenStartMessageColor"            : "#ffff66", 
  
  "GameSpawnEnemiesInitialDelta"            : 100, 
  "GameEnemiesInitialDropSpeed"             : 1, 
  "GameLifeSumDifferenceProportion"         : 10, 
  "GameLifeSubtractionDifferenceProportion" : 10, 
  "GameScoreSumFallDifference"              : 50, 
  "GameScoreSumHitDifference"               : 150, 
  "GameEnemiesDropSpeedDifference"          : 1, 
  "GameMaxEnemies"                          : 5, 
  "GameSpawnEnemiesDeltaDifference"         : 1, 
  "GamePauseMessageFont"                    : "48px PixelLife", 
  "GamePauseMessageColor"                   : "#ffffff", 
  "GamePauseMessageText"                    : "pause", 
  "GamePauseBackgroundColor"                : "#000000", 
  "GamePauseBackgroundOpacity"              : 0.5, 
  "GamePauseKeyCode"                        : 80, 
  
  "SceneryCloudsUpdateMaxDelta"             : 1, 
  "ScenerySkyUpdateMaxDelta"                : 1, 
  "SceneryToggleDaylightMaxDelta"           : 1000, 
  "SceneryUpdateRedFilterMaxDelta"          : 1, 
  "SceneryDestructionMaxDelta"              : 100, 
  "SceneryBigExplosionMaxDelta"             : 2, 
  "ScenerySkyDayColor"                      : "#b6f0ff", 
  "ScenerySkyNightColor"                    : "#335963", 
  "SceneryRedFilterSpeed"                   : 0.05, 
  "SceneryRedFilterMaxLevel"                : 0.5, 
  "SceneryRedFilterColor"                   : "#ff0000", 
  "SceneryBigExplosionColor"                : "#ffffff", 
  "SceneryBigExplosionSpeed"                : 15, 
  "SceneryBigExplosionHorizontalExtra"      : 125, 
  "SceneryBigExplosionVerticalExtra"        : 125, 
  
  "HUDLifeBarLeft"                          : 0, 
  "HUDLifeBarCenter"                        : 1, 
  "HUDLifeBarRight"                         : 2, 
  "HUDLifeBarLife"                          : 3, 
  "HUDCrosshairNormal"                      : 0, 
  "HUDCrosshairDetectedTarget"              : 1, 
  "HUDLifeUpdateMaxDelta"                   : 1, 
  "HUDScoreUpdateMaxDelta"                  : 1, 
  "HUDScoreBlinkMaxDelta"                   : 5, 
  "HUDScoreDifferenceUpdateMaxDelta"        : 1, 
  "HUDCrosshairPrecisionMaxDelta"           : 3, 
  "HUDVulnerableTargetCheckMaxDelta"        : 5, 
  "HUDLifeHorizontalOffset"                 : 3, 
  "HUDLifeUpdateSpeed"                      : 15, 
  "HUDScoreX"                               : 25, 
  "HUDScoreY"                               : 50, 
  "HUDScoreFont"                            : "48px PixelLife", 
  "HUDScoreColor"                           : "#000000", 
  "HUDScoreBlinkColor"                      : "#666666", 
  "HUDScorePrefix"                          : "SCORE ", 
  "HUDScoreUpdateSpeed"                     : 10, 
  "HUDScoreDifferenceX"                     : 25, 
  "HUDScoreDifferenceFont"                  : "48px PixelLife", 
  "HUDScoreDifferencePositiveColor"         : "#00ff00", 
  "HUDScoreDifferenceNegativeColor"         : "#ff0000", 
  "HUDScoreDifferenceStartY"                : 175, 
  "HUDScoreDifferenceEndY"                  : 100, 
  "HUDScoreDifferenceVerticalSpeed"         : 10, 
  "HUDScoreDifferenceOpacitySpeed"          : 0.075, 
  "HUDCrosshairPrecisionRatio"              : 10, 
  
  "ExplosionSpriteUpdateMaxDelta"           : 3, 
  "ExplosionRepeat"                         : 0, 
  
  "ShotSpriteIndex"                         : 0, 
  "ShotSpriteUpdateMaxDelta"                : 2, 
  "ShotRepeat"                              : 1, 

  "SplashSpriteIndex"                       : 0, 
  "SplashSpriteUpdateMaxDelta"              : 3, 
  "SplashRepeat"                            : 1, 
  
  "ParachuteDropUpdateMaxDelta"             : 5, 
  "ParachutePinchUpdateMaxDelta"            : 10, 
  "ParachuteHorizontalDisplacementMaxDelta" : 1, 
  "ParachuteHorizontalSpeed"                : 12, 
  
  "EnemyDropUpdateMaxDelta"                 : 5, 
  "EnemySpriteUpdateMaxDelta"               : 3, 
  "EnemyFreeFallMultiplication"             : 4, 
  
  "CreditsUpdateMaxDelta"                   : 1, 
  "CreditsSkipMessageMaxDelta"              : 15, 
  "CreditsSpeed"                            : 2, 
  "CreditsBackgroundColor"                  : "#333333", 
  "CreditsFont"                             : "48px PixelLife", 
  "CreditsColor"                            : "#ffffff", 
  "CreditsLineHeight"                       : 75, 
  "CreditsScoreTitle"                       : "your score is\n", 
  "CreditsLines"                            : "\n\nsnipe intruders\n\nprogramming and graphic design\nedgar alexander franco\n\ntypography\npixellife by william clifford\n\nused software\npiskel\nadobe photoshop cs3\nwincons\n\ngame testers\njeremy sthiven pacheco\nedgar samuel franco\n\nspecial thanks to\nmarta elena navasquez\n\nsupervised by\ngustavo jimenez\n\nproduced by\nedgar alexander franco\n\nthe characters in this game are fictitious and\nany resemblance to real persons living\n or dead is purely coincidental", 
  "CreditsSkipMessageText"                  : "click to skip", 
  "CreditsSkipMessageX"                     : 25, 
  "CreditsSkipMessageY"                     : 50, 
  "CreditsSkipMessageFont"                  : "48px PixelLife", 
  "CreditsSkipMessageColor"                 : "#ffff66"
}